DialogFlowPy/BasicCard.py
DialogFlowPy/BrowseCarouselCard.py
DialogFlowPy/BrowseCarouselCardItem.py
DialogFlowPy/Button.py
DialogFlowPy/Card.py
DialogFlowPy/CarouselItem.py
DialogFlowPy/CarouselSelect.py
DialogFlowPy/ColumnProperties.py
DialogFlowPy/Context.py
DialogFlowPy/DialogFlow.py
DialogFlowPy/Entity.py
DialogFlowPy/EventInput.py
DialogFlowPy/GooglePayload.py
DialogFlowPy/Image.py
DialogFlowPy/LinkOutSuggestion.py
DialogFlowPy/ListItem.py
DialogFlowPy/ListSelect.py
DialogFlowPy/MediaContent.py
DialogFlowPy/MediaObject.py
DialogFlowPy/Message.py
DialogFlowPy/OpenUriAction.py
DialogFlowPy/OpenUrlAction.py
DialogFlowPy/Payload.py
DialogFlowPy/QuickReplies.py
DialogFlowPy/SelectItemInfo.py
DialogFlowPy/SelectOptionInfo.py
DialogFlowPy/SessionEntityType.py
DialogFlowPy/SimpleResponse.py
DialogFlowPy/SimpleResponses.py
DialogFlowPy/Suggestion.py
DialogFlowPy/Suggestions.py
DialogFlowPy/TableCard.py
DialogFlowPy/TableCardCell.py
DialogFlowPy/TableCardRow.py
DialogFlowPy/Text.py
DialogFlowPy/__init__.py
DialogFlowPy/test/Unit Test.py
DialogFlowPy/test/__init__.py
DialogFlowPy-0.3.dist-info/LICENSE
DialogFlowPy-0.3.dist-info/METADATA
DialogFlowPy-0.3.dist-info/WHEEL
DialogFlowPy-0.3.dist-info/top_level.txt
DialogFlowPy-0.3.dist-info/RECORD
